slidefit.py
slidefit-0.2.1.dist-info/COPYING
slidefit-0.2.1.dist-info/METADATA
slidefit-0.2.1.dist-info/WHEEL
slidefit-0.2.1.dist-info/entry_points.txt
slidefit-0.2.1.dist-info/top_level.txt
slidefit-0.2.1.dist-info/RECORD
