Metadata-Version: 2.1
Name: slidefit
Version: 0.2.1
Summary: Fit images into slides
Home-page: https://github.com/tomnor/slidefit
Author: Tomas Nordin
Author-email: tomasn@posteo.net
License: GPLv3+
Keywords: slides presentation image productivity tool pptx
Platform: UNKNOWN
Classifier: Programming Language :: Python :: 3
Classifier: Environment :: Console
Classifier: Development Status :: 4 - Beta
Classifier: License :: OSI Approved :: GNU General Public License v3 or later (GPLv3+)
Classifier: Operating System :: OS Independent
Classifier: Topic :: Documentation
Classifier: Topic :: Office/Business
Classifier: Topic :: Utilities
Classifier: Topic :: Multimedia :: Graphics :: Presentation
Requires-Dist: docopt
Requires-Dist: python-pptx (>=0.6.22)
